alieneffects/__init__.py
alieneffects/config.py
alieneffects/constants.py
alieneffects/controller.py
alieneffects/theme.py
alieneffects/tui.py
alieneffects/usbdriver.py
alienware_13r3_alien_effects-0.2.2.data/scripts/alieneffects-13r3
alienware_13r3_alien_effects-0.2.2.dist-info/LICENSE
alienware_13r3_alien_effects-0.2.2.dist-info/METADATA
alienware_13r3_alien_effects-0.2.2.dist-info/WHEEL
alienware_13r3_alien_effects-0.2.2.dist-info/top_level.txt
alienware_13r3_alien_effects-0.2.2.dist-info/RECORD
