Metadata-Version: 2.1
Name: alienware-13r3-alien-effects
Version: 0.2.2
Summary: Backlight LED controller for alienware 13 R3
Home-page: https://github.com/Yashasvi-Sriram/alieneffects-13r3
Author: Yashasvi Sriram
Author-email: yash.3997@gmail.com
License: UNKNOWN
Platform: UNKNOWN
Classifier: Programming Language :: Python :: 3
